Metadata-Version: 2.1
Name: stratz
Version: 1.0.1
Summary: python lib for stratz.com
Home-page: https://github.com/fxckfxtxre/Stratz
Author: cxldxice
License: UNKNOWN
Keywords: stratz,dota,api
Platform: UNKNOWN
